ahk_json/JSON.ahk
ahk_json/Jxon.ahk
ahk_json/__init__.py
ahk_json/json.py
ahk_json/jxon.py
ahk_json/message.py
ahk_json/util.py
ahk_json-0.1.0rc2.dist-info/LICENSE
ahk_json-0.1.0rc2.dist-info/METADATA
ahk_json-0.1.0rc2.dist-info/WHEEL
ahk_json-0.1.0rc2.dist-info/top_level.txt
ahk_json-0.1.0rc2.dist-info/RECORD
