Metadata-Version: 2.1
Name: ahk-json
Version: 0.1.0rc2
Summary: Auto-Hotkey-JSON for Python
Home-page: https://github.com/spyoungtech/ahk-json
Author: Spencer Young
Author-email: spencer.young@spyoung.com
Keywords: ahk,autohotkey,jxon,json,python
Classifier: Intended Audience :: Developers
Classifier: Topic :: Desktop Environment
Classifier: Programming Language :: Python
Classifier: Environment :: Win32 (MS Windows)
Classifier: License :: OSI Approved :: MIT License
Classifier: Operating System :: Microsoft :: Windows
Classifier: Programming Language :: Python :: 3 :: Only
Classifier: Programming Language :: Python :: 3.8
Classifier: Programming Language :: Python :: 3.9
Classifier: Programming Language :: Python :: 3.10
Classifier: Programming Language :: Python :: 3.11
Requires-Python: >=3.8.0
License-File: LICENSE
Requires-Dist: ahk
